discreteMarkovChain/__init__.py
discreteMarkovChain/examples.py
discreteMarkovChain/markovChain.py
discreteMarkovChain/usefulFunctions.py
discreteMarkovChain-0.22.dist-info/DESCRIPTION.rst
discreteMarkovChain-0.22.dist-info/METADATA
discreteMarkovChain-0.22.dist-info/RECORD
discreteMarkovChain-0.22.dist-info/WHEEL
discreteMarkovChain-0.22.dist-info/metadata.json
discreteMarkovChain-0.22.dist-info/top_level.txt
