Metadata-Version: 2.0
Name: discreteMarkovChain
Version: 0.22
Summary: Solve Markov chains with a discrete state space.
Home-page: https://github.com/gvanderheide/discreteMarkovChain
Author: Gerlach van der Heide
Author-email: g.van.der.heide@rug.nl
License: MIT
Keywords: Markov chain stochastic stationary steady state
Platform: UNKNOWN
Classifier: Development Status :: 3 - Alpha
Classifier: Intended Audience :: Developers
Classifier: Intended Audience :: Education
Classifier: Intended Audience :: Science/Research
Classifier: Topic :: Scientific/Engineering :: Mathematics
Classifier: License :: OSI Approved :: MIT License
Classifier: Programming Language :: Python
Classifier: Programming Language :: Python :: 2
Classifier: Programming Language :: Python :: 2.7
Classifier: Programming Language :: Python :: 3
Classifier: Programming Language :: Python :: 3.5
Classifier: Operating System :: OS Independent
Requires-Dist: numpy
Requires-Dist: scipy
